README
setup.py
clipy/__init__.py
clipy/argparse.py
clipy/command.py
clipy/loader.py
clipy/utils.py
clipy.egg-info/PKG-INFO
clipy.egg-info/SOURCES.txt
clipy.egg-info/dependency_links.txt
clipy.egg-info/entry_points.txt
clipy.egg-info/requires.txt
clipy.egg-info/top_level.txt
clipy.egg-info/zip-safe
clipy/tests/__init__.py