Metadata-Version: 1.0
Name: clipy
Version: 0.4
Summary: Library for creating command line interfaces
Home-page: UNKNOWN
Author: Andrey Popp
Author-email: 8mayday@gmail.com
License: MIT
Keywords: python cli framework cmd command line interface
Platform: UNKNOWN
Classifier: Development Status :: 3 - Alpha
Classifier: Environment :: Console
Classifier: Intended Audience :: Developers
Classifier: License :: OSI Approved :: MIT License
Classifier: Natural Language :: English
Classifier: Operating System :: OS Independent
Classifier: Programming Language :: Python
Classifier: Topic :: Software Development :: Libraries :: Python Modules
